elegantt/__init__.py
elegantt/command.py
elegantt/elegantt.py
elegantt/utils.py
elegantt-0.0.11.dist-info/LICENSE
elegantt-0.0.11.dist-info/METADATA
elegantt-0.0.11.dist-info/WHEEL
elegantt-0.0.11.dist-info/entry_points.txt
elegantt-0.0.11.dist-info/top_level.txt
elegantt-0.0.11.dist-info/RECORD
