Metadata-Version: 2.1
Name: elegantt
Version: 0.0.11
Summary: This is a gantt chart drawing library
Home-page: http://github.com/usop4/elegantt
Author: Takayuki Uehara
Author-email: t.uehara@gmail.com
License: UNKNOWN
Platform: UNKNOWN
Classifier: License :: OSI Approved :: MIT License
Classifier: Programming Language :: Python :: 3
Classifier: Programming Language :: Python :: 3.8
Classifier: Operating System :: OS Independent
Requires-Python: ~=3.8
License-File: LICENSE
Requires-Dist: Pillow<11.1,>=10.4.0
Requires-Dist: Pandas
Requires-Dist: Fire
